medscan/__init__.py
medscan/config.py
medscan/data.py
medscan/pipeline.py
medscan/predict.py
medscan/train.py
medscan/transform.py
medscan_cu121-0.1.2.dist-info/METADATA
medscan_cu121-0.1.2.dist-info/WHEEL
medscan_cu121-0.1.2.dist-info/top_level.txt
medscan_cu121-0.1.2.dist-info/RECORD
